Uart/uart_rx.v
//////////////////////////////////////////////////////////////////////////////////
// Uart Receiver Module
// Author: Ayushi Maurya
// Clock frequency: 50MHz
// Clock per bit: 217 (for 230400 baud rate)
// just for learning purpose
//////////////////////////////////////////////////////////////////////////////////

module uart_rx #(parameter CLKS_PER_BIT = 217) 
(
    input i_rst_l, // active low reset
    input sys_clk, // system clock
    input i_rx_serial, // Uart serial input
    output reg o_rx_DV, // data high for full byte received
    output reg [7:0] o_rx_data // data received
);

// encoding the states of the state machine
localparam IDLE       = 3'b000;
localparam Start_bit   = 3'b001;
localparam Data_bits  = 3'b010;
localparam Stop_bit   = 3'b011;
localparam Clean      = 3'b100;


// some registers in the module
reg [2:0] state =IDLE;
reg [$clog2(CLKS_PER_BIT)-1:0] clk_count =0; // counter for the clock cycles in one bit]
reg [2:0] bit_index =0; // index of the bit being received

// state machine
always @(posedge sys_clk or negedge i_rst_l)
    begin 
        if (~i_rst_l)
        begin
            state <= 3'b000;
            o_rx_DV <= 1'b0;  // data valid cleared
        end 

        else
            begin
                case (state)
                IDLE: 
                begin 
                    o_rx_DV <=1'b0; 
                    clk_count <=0;
                    bit_index <=0;

                    if (i_rx_serial == 1'b0) // start bit detected
                        state <=Start_bit;
                    else
                        state<=IDLE;
                end
                Start_bit:
                begin 
                    if (clk_count == (CLKS_PER_BIT-1)/2) // middle check 
                    begin 
                        if (i_rx_serial == 1'b0) // low found at middle
                        begin 
                            clk_count <=0;
                            state <= Data_bits; // 
                        end
                        else
                            state <= IDLE; // false start bit
                    end
                    else
                    begin 
                        clk_count <= clk_count+1;
                        state <= Start_bit;
                    end
                end

                Data_bits:
                begin 
                    if (clk_count < CLKS_PER_BIT-1)  // wait for full bit period
                    begin
                        clk_count <= clk_count +1;
                        state <= Data_bits;
                    end
                    else
                    begin 
                        clk_count <= 0;
                        o_rx_data[bit_index] <= i_rx_serial;
                        if (bit_index < 7 )
                        begin 
                            bit_index <= bit_index+1;
                            state <=Data_bits;
                        end
                        else
                        begin 
                            bit_index <=0;
                            state <= Stop_bit;
                        end
                    end
                end
                Stop_bit:
                begin 
                    if (clk_count <= CLKS_PER_BIT-1)
                    begin
                        clk_count <= clk_count +1;
                        state <= Stop_bit;
                    end
                    else 
                    begin
                         clk_count <=0;
                    o_rx_DV <=1'b1; // data valid
                    state <= Clean;
                    end
                   
                end 
                Clean:
                begin 
                    state<= IDLE;
                    o_rx_DV <=1'b0;
                end
                default:
                    state <= IDLE;
                endcase

    end
end




endmodule

Uart/uart_tx.v
module UART_Tx #(parameter CLKS_PER_BIT = 217) 
 (
    input i_rst_l,  //Active low reset
    input i_clk_sys,  // System clock
    input i_tx_start, // sending the data is valid
    input [7:0] i_tx_byte, // data to be sent
    output reg o_tx_active, // low when idle, high when transmitting data
    output reg o_tx_serial, // UART serial out
    output reg o_tx_done // high for 1 clock cycle when transmission is done
 );

// parameter for the state machine

 localparam IDLE        = 3'b000;  // line high (Uart waits for start bit)
 localparam Start_bit   = 3'b001;  // line low (tx start) start bit =0 
 localparam Data_bits   = 3'b010;  // 8 data bits (LSB first)
 localparam Stop_bit    = 3'b011; // tx stop sending sero bit first
 localparam Clean       = 3'b100;  // finish tx


// some registers in the module
reg [2:0] state = 0; // current state
reg [$clog2(CLKS_PER_BIT)-1:0] clk_count =0; // counter for the clock cycles in one bit
reg [2:0] bit_index =0; // index of the bit being sent 
reg [7:0] tx_data =0; // data being sent

//state machine
always @(posedge i_clk_sys or negedge i_rst_l) 
   begin
        if (~i_rst_l)
        begin 
            state <= 3'b000;
        end
        else
        begin 
            o_tx_done <= 1'b0; // default value
            case (state)
            IDLE:
                    begin 
                        o_tx_serial <= 1'b1; // line is high -> idle
                        clk_count <=0;  // counts the clock cycles in one bit
                        bit_index <=0;  // index of the bit being sent
                        if (i_tx_start == 1'b1) 
                        begin
                            o_tx_active <= 1'b1; // transmission is active
                            tx_data <= i_tx_byte; // load the data to be sent
                            state <= Start_bit;  // go to start bit state
                        end
                    else begin
                        state <= IDLE;
                        o_tx_active <= 1'b0;
                    end
                    end
            Start_bit:
                    begin
                        o_tx_serial <=1'b0; //start bit
                        if (clk_count < CLKS_PER_BIT -1) 
                            clk_count <= clk_count+1;
                        else
                        begin
                            clk_count <=0;
                            state <= Data_bits;
                        end
                    end
            Data_bits:
                    begin
                        o_tx_serial <= tx_data[bit_index]; //send the data bit]
                        if (clk_count < CLKS_PER_BIT -1) 
                        begin 
                            clk_count <= clk_count +1;
                        end

                        else
                        begin
                            clk_count <=0;
                            if (bit_index < 7)
                            begin 
                                bit_index <= bit_index +1;
                            end
                            else begin 
                                bit_index <=0;
                                state <= Stop_bit;
                            end
                        end
                    end
        Stop_bit:
        begin 
            o_tx_serial <= 1'b1; // stop_bit =1;

            if (clk_count < CLKS_PER_BIT-1)
            begin
                clk_count <= clk_count +1;
            
            end

            else 
            begin 
                o_tx_done <= 1'b1; // signal done
                clk_count <= 0;
                state <= Clean;
                o_tx_active <=1'b0; // no longer transmitting

            end
        end

        Clean:

        begin
            state <= IDLE;
        end

        default: state <= IDLE;
                
            

    endcase
    end
end

endmodule

Uart/uart_tb.v
`timescale 1ns/1ps

module uart_tb;

  parameter CLKS_PER_BIT = 217;

  // Signals
  reg clk = 0;
  reg rst_n = 0;
  reg tx_start = 0;
  reg [7:0] tx_data = 8'hFF; // Example data byte to transmit

  wire tx_serial;
  wire tx_done;
  wire tx_active;
  wire rx_dv;
  wire [7:0] rx_data;

  // 50 MHz clock = 20 ns period
  always #10 clk = ~clk;

  // Instantiate UART Transmitter
  UART_Tx #(.CLKS_PER_BIT(CLKS_PER_BIT)) tx_inst (
    .i_rst_l     (rst_n),
    .i_clk_sys   (clk),
    .i_tx_start  (tx_start),
    .i_tx_byte   (tx_data),
    .o_tx_active (tx_active),
    .o_tx_serial (tx_serial),
    .o_tx_done   (tx_done)
  );

  // Instantiate UART Receiver
  uart_rx #(.CLKS_PER_BIT(CLKS_PER_BIT)) rx_inst (
    .i_rst_l     (rst_n),
    .sys_clk     (clk),
    .i_rx_serial (tx_serial),
    .o_rx_DV     (rx_dv),
    .o_rx_data   (rx_data)
  );

  // Test sequence
  initial begin
    $dumpfile("uart_wave.vcd");
    $dumpvars(0, uart_tb);

    // Reset
    rst_n = 0;
    #100;
    rst_n = 1;

    // Start transmission
    #200;
    tx_start = 1;
    #20;
    tx_start = 0;

    // Wait for transfer to complete
    #50000;
    $finish;
  end

endmodule

Uart/waveform/uart_wave.vcd
$date
	Wed Oct 08 22:51:59 2025
$end
$version
	Icarus Verilog
$end
$timescale
	1ps
$end
$scope module uart_tb $end
$var wire 1 ! tx_serial $end
$var wire 1 " tx_done $end
$var wire 1 # tx_active $end
$var wire 1 $ rx_dv $end
$var wire 8 % rx_data [7:0] $end
$var parameter 32 & CLKS_PER_BIT $end
$var reg 1 ' clk $end
$var reg 1 ( rst_n $end
$var reg 8 ) tx_data [7:0] $end
$var reg 1 * tx_start $end
$scope module rx_inst $end
$var wire 1 ( i_rst_l $end
$var wire 1 ' sys_clk $end
$var wire 1 ! i_rx_serial $end
$var parameter 32 + CLKS_PER_BIT $end
$var parameter 3 , Clean $end
$var parameter 3 - Data_bits $end
$var parameter 3 . IDLE $end
$var parameter 3 / Start_bit $end
$var parameter 3 0 Stop_bit $end
$var reg 3 1 bit_index [2:0] $end
$var reg 8 2 clk_count [7:0] $end
$var reg 1 $ o_rx_DV $end
$var reg 8 3 o_rx_data [7:0] $end
$var reg 3 4 state [2:0] $end
$upscope $end
$scope module tx_inst $end
$var wire 1 ' i_clk_sys $end
$var wire 1 ( i_rst_l $end
$var wire 8 5 i_tx_byte [7:0] $end
$var wire 1 * i_tx_start $end
$var parameter 32 6 CLKS_PER_BIT $end
$var parameter 3 7 Clean $end
$var parameter 3 8 Data_bits $end
$var parameter 3 9 IDLE $end
$var parameter 3 : Start_bit $end
$var parameter 3 ; Stop_bit $end
$var reg 3 < bit_index [2:0] $end
$var reg 8 = clk_count [7:0] $end
$var reg 1 # o_tx_active $end
$var reg 1 " o_tx_done $end
$var reg 1 ! o_tx_serial $end
$var reg 3 > state [2:0] $end
$var reg 8 ? tx_data [7:0] $end
$upscope $end
$upscope $end
$enddefinitions $end
$comment Show the parameter values. $end
$dumpall
b11 ;
b1 :
b0 9
b10 8
b100 7
b11011001 6
b11 0
b1 /
b0 .
b10 -
b100 ,
b11011001 +
b11011001 &
$end
#0
$dumpvars
b0 ?
b0 >
b0 =
b0 <
b11111111 5
b0 4
bx 3
b0 2
b0 1
0*
b11111111 )
0(
0'
bx %
0$
x#
x"
x!
$end
#10000
1'
#20000
0'
#30000
1'
#40000
0'
#50000
1'
#60000
0'
#70000
1'
#80000
0'
#90000
1'
#100000
0'
1(
#110000
0#
1!
0"
1'
#120000
0'
#130000
1'
#140000
0'
#150000
1'
#160000
0'
#170000
1'
#180000
0'
#190000
1'
#200000
0'
#210000
1'
#220000
0'
#230000
1'
#240000
0'
#250000
1'
#260000
0'
#270000
1'
#280000
0'
#290000
1'
#300000
0'
1*
#310000
b1 >
b11111111 ?
1#
1'
#320000
0'
0*
#330000
b1 =
0!
1'
#340000
0'
#350000
b10 =
b1 4
1'
#360000
0'
#370000
b1 2
b11 =
1'
#380000
0'
#390000
b100 =
b10 2
1'
#400000
0'
#410000
b11 2
b101 =
1'
#420000
0'
#430000
b110 =
b100 2
1'
#440000
0'
#450000
b101 2
b111 =
1'
#460000
0'
#470000
b1000 =
b110 2
1'
#480000
0'
#490000
b111 2
b1001 =
1'
#500000
0'
#510000
b1010 =
b1000 2
1'
#520000
0'
#530000
b1001 2
b1011 =
1'
#540000
0'
#550000
b1100 =
b1010 2
1'
#560000
0'
#570000
b1011 2
b1101 =
1'
#580000
0'
#590000
b1110 =
b1100 2
1'
#600000
0'
#610000
b1101 2
b1111 =
1'
#620000
0'
#630000
b10000 =
b1110 2
1'
#640000
0'
#650000
b1111 2
b10001 =
1'
#660000
0'
#670000
b10010 =
b10000 2
1'
#680000
0'
#690000
b10001 2
b10011 =
1'
#700000
0'
#710000
b10100 =
b10010 2
1'
#720000
0'
#730000
b10011 2
b10101 =
1'
#740000
0'
#750000
b10110 =
b10100 2
1'
#760000
0'
#770000
b10101 2
b10111 =
1'
#780000
0'
#790000
b11000 =
b10110 2
1'
#800000
0'
#810000
b10111 2
b11001 =
1'
#820000
0'
#830000
b11010 =
b11000 2
1'
#840000
0'
#850000
b11001 2
b11011 =
1'
#860000
0'
#870000
b11100 =
b11010 2
1'
#880000
0'
#890000
b11011 2
b11101 =
1'
#900000
0'
#910000
b11110 =
b11100 2
1'
#920000
0'
#930000
b11101 2
b11111 =
1'
#940000
0'
#950000
b100000 =
b11110 2
1'
#960000
0'
#970000
b11111 2
b100001 =
1'
#980000
0'
#990000
b100010 =
b100000 2
1'
#1000000
0'
#1010000
b100001 2
b100011 =
1'
#1020000
0'
#1030000
b100100 =
b100010 2
1'
#1040000
0'
#1050000
b100011 2
b100101 =
1'
#1060000
0'
#1070000
b100110 =
b100100 2
1'
#1080000
0'
#1090000
b100101 2
b100111 =
1'
#1100000
0'
#1110000
b101000 =
b100110 2
1'
#1120000
0'
#1130000
b100111 2
b101001 =
1'
#1140000
0'
#1150000
b101010 =
b101000 2
1'
#1160000
0'
#1170000
b101001 2
b101011 =
1'
#1180000
0'
#1190000
b101100 =
b101010 2
1'
#1200000
0'
#1210000
b101011 2
b101101 =
1'
#1220000
0'
#1230000
b101110 =
b101100 2
1'
#1240000
0'
#1250000
b101101 2
b101111 =
1'
#1260000
0'
#1270000
b110000 =
b101110 2
1'
#1280000
0'
#1290000
b101111 2
b110001 =
1'
#1300000
0'
#1310000
b110010 =
b110000 2
1'
#1320000
0'
#1330000
b110001 2
b110011 =
1'
#1340000
0'
#1350000
b110100 =
b110010 2
1'
#1360000
0'
#1370000
b110011 2
b110101 =
1'
#1380000
0'
#1390000
b110110 =
b110100 2
1'
#1400000
0'
#1410000
b110101 2
b110111 =
1'
#1420000
0'
#1430000
b111000 =
b110110 2
1'
#1440000
0'
#1450000
b110111 2
b111001 =
1'
#1460000
0'
#1470000
b111010 =
b111000 2
1'
#1480000
0'
#1490000
b111001 2
b111011 =
1'
#1500000
0'
#1510000
b111100 =
b111010 2
1'
#1520000
0'
#1530000
b111011 2
b111101 =
1'
#1540000
0'
#1550000
b111110 =
b111100 2
1'
#1560000
0'
#1570000
b111101 2
b111111 =
1'
#1580000
0'
#1590000
b1000000 =
b111110 2
1'
#1600000
0'
#1610000
b111111 2
b1000001 =
1'
#1620000
0'
#1630000
b1000010 =
b1000000 2
1'
#1640000
0'
#1650000
b1000001 2
b1000011 =
1'
#1660000
0'
#1670000
b1000100 =
b1000010 2
1'
#1680000
0'
#1690000
b1000011 2
b1000101 =
1'
#1700000
0'
#1710000
b1000110 =
b1000100 2
1'
#1720000
0'
#1730000
b1000101 2
b1000111 =
1'
#1740000
0'
#1750000
b1001000 =
b1000110 2
1'
#1760000
0'
#1770000
b1000111 2
b1001001 =
1'
#1780000
0'
#1790000
b1001010 =
b1001000 2
1'
#1800000
0'
#1810000
b1001001 2
b1001011 =
1'
#1820000
0'
#1830000
b1001100 =
b1001010 2
1'
#1840000
0'
#1850000
b1001011 2
b1001101 =
1'
#1860000
0'
#1870000
b1001110 =
b1001100 2
1'
#1880000
0'
#1890000
b1001101 2
b1001111 =
1'
#1900000
0'
#1910000
b1010000 =
b1001110 2
1'
#1920000
0'
#1930000
b1001111 2
b1010001 =
1'
#1940000
0'
#1950000
b1010010 =
b1010000 2
1'
#1960000
0'
#1970000
b1010001 2
b1010011 =
1'
#1980000
0'
#1990000
b1010100 =
b1010010 2
1'
#2000000
0'
#2010000
b1010011 2
b1010101 =
1'
#2020000
0'
#2030000
b1010110 =
b1010100 2
1'
#2040000
0'
#2050000
b1010101 2
b1010111 =
1'
#2060000
0'
#2070000
b1011000 =
b1010110 2
1'
#2080000
0'
#2090000
b1010111 2
b1011001 =
1'
#2100000
0'
#2110000
b1011010 =
b1011000 2
1'
#2120000
0'
#2130000
b1011001 2
b1011011 =
1'
#2140000
0'
#2150000
b1011100 =
b1011010 2
1'
#2160000
0'
#2170000
b1011011 2
b1011101 =
1'
#2180000
0'
#2190000
b1011110 =
b1011100 2
1'
#2200000
0'
#2210000
b1011101 2
b1011111 =
1'
#2220000
0'
#2230000
b1100000 =
b1011110 2
1'
#2240000
0'
#2250000
b1011111 2
b1100001 =
1'
#2260000
0'
#2270000
b1100010 =
b1100000 2
1'
#2280000
0'
#2290000
b1100001 2
b1100011 =
1'
#2300000
0'
#2310000
b1100100 =
b1100010 2
1'
#2320000
0'
#2330000
b1100011 2
b1100101 =
1'
#2340000
0'
#2350000
b1100110 =
b1100100 2
1'
#2360000
0'
#2370000
b1100101 2
b1100111 =
1'
#2380000
0'
#2390000
b1101000 =
b1100110 2
1'
#2400000
0'
#2410000
b1100111 2
b1101001 =
1'
#2420000
0'
#2430000
b1101010 =
b1101000 2
1'
#2440000
0'
#2450000
b1101001 2
b1101011 =
1'
#2460000
0'
#2470000
b1101100 =
b1101010 2
1'
#2480000
0'
#2490000
b1101011 2
b1101101 =
1'
#2500000
0'
#2510000
b1101110 =
b1101100 2
1'
#2520000
0'
#2530000
b10 4
b0 2
b1101111 =
1'
#2540000
0'
#2550000
b1110000 =
b1 2
1'
#2560000
0'
#2570000
b10 2
b1110001 =
1'
#2580000
0'
#2590000
b1110010 =
b11 2
1'
#2600000
0'
#2610000
b100 2
b1110011 =
1'
#2620000
0'
#2630000
b1110100 =
b101 2
1'
#2640000
0'
#2650000
b110 2
b1110101 =
1'
#2660000
0'
#2670000
b1110110 =
b111 2
1'
#2680000
0'
#2690000
b1000 2
b1110111 =
1'
#2700000
0'
#2710000
b1111000 =
b1001 2
1'
#2720000
0'
#2730000
b1010 2
b1111001 =
1'
#2740000
0'
#2750000
b1111010 =
b1011 2
1'
#2760000
0'
#2770000
b1100 2
b1111011 =
1'
#2780000
0'
#2790000
b1111100 =
b1101 2
1'
#2800000
0'
#2810000
b1110 2
b1111101 =
1'
#2820000
0'
#2830000
b1111110 =
b1111 2
1'
#2840000
0'
#2850000
b10000 2
b1111111 =
1'
#2860000
0'
#2870000
b10000000 =
b10001 2
1'
#2880000
0'
#2890000
b10010 2
b10000001 =
1'
#2900000
0'
#2910000
b10000010 =
b10011 2
1'
#2920000
0'
#2930000
b10100 2
b10000011 =
1'
#2940000
0'
#2950000
b10000100 =
b10101 2
1'
#2960000
0'
#2970000
b10110 2
b10000101 =
1'
#2980000
0'
#2990000
b10000110 =
b10111 2
1'
#3000000
0'
#3010000
b11000 2
b10000111 =
1'
#3020000
0'
#3030000
b10001000 =
b11001 2
1'
#3040000
0'
#3050000
b11010 2
b10001001 =
1'
#3060000
0'
#3070000
b10001010 =
b11011 2
1'
#3080000
0'
#3090000
b11100 2
b10001011 =
1'
#3100000
0'
#3110000
b10001100 =
b11101 2
1'
#3120000
0'
#3130000
b11110 2
b10001101 =
1'
#3140000
0'
#3150000
b10001110 =
b11111 2
1'
#3160000
0'
#3170000
b100000 2
b10001111 =
1'
#3180000
0'
#3190000
b10010000 =
b100001 2
1'
#3200000
0'
#3210000
b100010 2
b10010001 =
1'
#3220000
0'
#3230000
b10010010 =
b100011 2
1'
#3240000
0'
#3250000
b100100 2
b10010011 =
1'
#3260000
0'
#3270000
b10010100 =
b100101 2
1'
#3280000
0'
#3290000
b100110 2
b10010101 =
1'
#3300000
0'
#3310000
b10010110 =
b100111 2
1'
#3320000
0'
#3330000
b101000 2
b10010111 =
1'
#3340000
0'
#3350000
b10011000 =
b101001 2
1'
#3360000
0'
#3370000
b101010 2
b10011001 =
1'
#3380000
0'
#3390000
b10011010 =
b101011 2
1'
#3400000
0'
#3410000
b101100 2
b10011011 =
1'
#3420000
0'
#3430000
b10011100 =
b101101 2
1'
#3440000
0'
#3450000
b101110 2
b10011101 =
1'
#3460000
0'
#3470000
b10011110 =
b101111 2
1'
#3480000
0'
#3490000
b110000 2
b10011111 =
1'
#3500000
0'
#3510000
b10100000 =
b110001 2
1'
#3520000
0'
#3530000
b110010 2
b10100001 =
1'
#3540000
0'
#3550000
b10100010 =
b110011 2
1'
#3560000
0'
#3570000
b110100 2
b10100011 =
1'
#3580000
0'
#3590000
b10100100 =
b110101 2
1'
#3600000
0'
#3610000
b110110 2
b10100101 =
1'
#3620000
0'
#3630000
b10100110 =
b110111 2
1'
#3640000
0'
#3650000
b111000 2
b10100111 =
1'
#3660000
0'
#3670000
b10101000 =
b111001 2
1'
#3680000
0'
#3690000
b111010 2
b10101001 =
1'
#3700000
0'
#3710000
b10101010 =
b111011 2
1'
#3720000
0'
#3730000
b111100 2
b10101011 =
1'
#3740000
0'
#3750000
b10101100 =
b111101 2
1'
#3760000
0'
#3770000
b111110 2
b10101101 =
1'
#3780000
0'
#3790000
b10101110 =
b111111 2
1'
#3800000
0'
#3810000
b1000000 2
b10101111 =
1'
#3820000
0'
#3830000
b10110000 =
b1000001 2
1'
#3840000
0'
#3850000
b1000010 2
b10110001 =
1'
#3860000
0'
#3870000
b10110010 =
b1000011 2
1'
#3880000
0'
#3890000
b1000100 2
b10110011 =
1'
#3900000
0'
#3910000
b10110100 =
b1000101 2
1'
#3920000
0'
#3930000
b1000110 2
b10110101 =
1'
#3940000
0'
#3950000
b10110110 =
b1000111 2
1'
#3960000
0'
#3970000
b1001000 2
b10110111 =
1'
#3980000
0'
#3990000
b10111000 =
b1001001 2
1'
#4000000
0'
#4010000
b1001010 2
b10111001 =
1'
#4020000
0'
#4030000
b10111010 =
b1001011 2
1'
#4040000
0'
#4050000
b1001100 2
b10111011 =
1'
#4060000
0'
#4070000
b10111100 =
b1001101 2
1'
#4080000
0'
#4090000
b1001110 2
b10111101 =
1'
#4100000
0'
#4110000
b10111110 =
b1001111 2
1'
#4120000
0'
#4130000
b1010000 2
b10111111 =
1'
#4140000
0'
#4150000
b11000000 =
b1010001 2
1'
#4160000
0'
#4170000
b1010010 2
b11000001 =
1'
#4180000
0'
#4190000
b11000010 =
b1010011 2
1'
#4200000
0'
#4210000
b1010100 2
b11000011 =
1'
#4220000
0'
#4230000
b11000100 =
b1010101 2
1'
#4240000
0'
#4250000
b1010110 2
b11000101 =
1'
#4260000
0'
#4270000
b11000110 =
b1010111 2
1'
#4280000
0'
#4290000
b1011000 2
b11000111 =
1'
#4300000
0'
#4310000
b11001000 =
b1011001 2
1'
#4320000
0'
#4330000
b1011010 2
b11001001 =
1'
#4340000
0'
#4350000
b11001010 =
b1011011 2
1'
#4360000
0'
#4370000
b1011100 2
b11001011 =
1'
#4380000
0'
#4390000
b11001100 =
b1011101 2
1'
#4400000
0'
#4410000
b1011110 2
b11001101 =
1'
#4420000
0'
#4430000
b11001110 =
b1011111 2
1'
#4440000
0'
#4450000
b1100000 2
b11001111 =
1'
#4460000
0'
#4470000
b11010000 =
b1100001 2
1'
#4480000
0'
#4490000
b1100010 2
b11010001 =
1'
#4500000
0'
#4510000
b11010010 =
b1100011 2
1'
#4520000
0'
#4530000
b1100100 2
b11010011 =
1'
#4540000
0'
#4550000
b11010100 =
b1100101 2
1'
#4560000
0'
#4570000
b1100110 2
b11010101 =
1'
#4580000
0'
#4590000
b11010110 =
b1100111 2
1'
#4600000
0'
#4610000
b1101000 2
b11010111 =
1'
#4620000
0'
#4630000
b11011000 =
b1101001 2
1'
#4640000
0'
#4650000
b1101010 2
b10 >
b0 =
1'
#4660000
0'
#4670000
b1 =
1!
b1101011 2
1'
#4680000
0'
#4690000
b1101100 2
b10 =
1'
#4700000
0'
#4710000
b11 =
b1101101 2
1'
#4720000
0'
#4730000
b1101110 2
b100 =
1'
#4740000
0'
#4750000
b101 =
b1101111 2
1'
#4760000
0'
#4770000
b1110000 2
b110 =
1'
#4780000
0'
#4790000
b111 =
b1110001 2
1'
#4800000
0'
#4810000
b1110010 2
b1000 =
1'
#4820000
0'
#4830000
b1001 =
b1110011 2
1'
#4840000
0'
#4850000
b1110100 2
b1010 =
1'
#4860000
0'
#4870000
b1011 =
b1110101 2
1'
#4880000
0'
#4890000
b1110110 2
b1100 =
1'
#4900000
0'
#4910000
b1101 =
b1110111 2
1'
#4920000
0'
#4930000
b1111000 2
b1110 =
1'
#4940000
0'
#4950000
b1111 =
b1111001 2
1'
#4960000
0'
#4970000
b1111010 2
b10000 =
1'
#4980000
0'
#4990000
b10001 =
b1111011 2
1'
#5000000
0'
#5010000
b1111100 2
b10010 =
1'
#5020000
0'
#5030000
b10011 =
b1111101 2
1'
#5040000
0'
#5050000
b1111110 2
b10100 =
1'
#5060000
0'
#5070000
b10101 =
b1111111 2
1'
#5080000
0'
#5090000
b10000000 2
b10110 =
1'
#5100000
0'
#5110000
b10111 =
b10000001 2
1'
#5120000
0'
#5130000
b10000010 2
b11000 =
1'
#5140000
0'
#5150000
b11001 =
b10000011 2
1'
#5160000
0'
#5170000
b10000100 2
b11010 =
1'
#5180000
0'
#5190000
b11011 =
b10000101 2
1'
#5200000
0'
#5210000
b10000110 2
b11100 =
1'
#5220000
0'
#5230000
b11101 =
b10000111 2
1'
#5240000
0'
#5250000
b10001000 2
b11110 =
1'
#5260000
0'
#5270000
b11111 =
b10001001 2
1'
#5280000
0'
#5290000
b10001010 2
b100000 =
1'
#5300000
0'
#5310000
b100001 =
b10001011 2
1'
#5320000
0'
#5330000
b10001100 2
b100010 =
1'
#5340000
0'
#5350000
b100011 =
b10001101 2
1'
#5360000
0'
#5370000
b10001110 2
b100100 =
1'
#5380000
0'
#5390000
b100101 =
b10001111 2
1'
#5400000
0'
#5410000
b10010000 2
b100110 =
1'
#5420000
0'
#5430000
b100111 =
b10010001 2
1'
#5440000
0'
#5450000
b10010010 2
b101000 =
1'
#5460000
0'
#5470000
b101001 =
b10010011 2
1'
#5480000
0'
#5490000
b10010100 2
b101010 =
1'
#5500000
0'
#5510000
b101011 =
b10010101 2
1'
#5520000
0'
#5530000
b10010110 2
b101100 =
1'
#5540000
0'
#5550000
b101101 =
b10010111 2
1'
#5560000
0'
#5570000
b10011000 2
b101110 =
1'
#5580000
0'
#5590000
b101111 =
b10011001 2
1'
#5600000
0'
#5610000
b10011010 2
b110000 =
1'
#5620000
0'
#5630000
b110001 =
b10011011 2
1'
#5640000
0'
#5650000
b10011100 2
b110010 =
1'
#5660000
0'
#5670000
b110011 =
b10011101 2
1'
#5680000
0'
#5690000
b10011110 2
b110100 =
1'
#5700000
0'
#5710000
b110101 =
b10011111 2
1'
#5720000
0'
#5730000
b10100000 2
b110110 =
1'
#5740000
0'
#5750000
b110111 =
b10100001 2
1'
#5760000
0'
#5770000
b10100010 2
b111000 =
1'
#5780000
0'
#5790000
b111001 =
b10100011 2
1'
#5800000
0'
#5810000
b10100100 2
b111010 =
1'
#5820000
0'
#5830000
b111011 =
b10100101 2
1'
#5840000
0'
#5850000
b10100110 2
b111100 =
1'
#5860000
0'
#5870000
b111101 =
b10100111 2
1'
#5880000
0'
#5890000
b10101000 2
b111110 =
1'
#5900000
0'
#5910000
b111111 =
b10101001 2
1'
#5920000
0'
#5930000
b10101010 2
b1000000 =
1'
#5940000
0'
#5950000
b1000001 =
b10101011 2
1'
#5960000
0'
#5970000
b10101100 2
b1000010 =
1'
#5980000
0'
#5990000
b1000011 =
b10101101 2
1'
#6000000
0'
#6010000
b10101110 2
b1000100 =
1'
#6020000
0'
#6030000
b1000101 =
b10101111 2
1'
#6040000
0'
#6050000
b10110000 2
b1000110 =
1'
#6060000
0'
#6070000
b1000111 =
b10110001 2
1'
#6080000
0'
#6090000
b10110010 2
b1001000 =
1'
#6100000
0'
#6110000
b1001001 =
b10110011 2
1'
#6120000
0'
#6130000
b10110100 2
b1001010 =
1'
#6140000
0'
#6150000
b1001011 =
b10110101 2
1'
#6160000
0'
#6170000
b10110110 2
b1001100 =
1'
#6180000
0'
#6190000
b1001101 =
b10110111 2
1'
#6200000
0'
#6210000
b10111000 2
b1001110 =
1'
#6220000
0'
#6230000
b1001111 =
b10111001 2
1'
#6240000
0'
#6250000
b10111010 2
b1010000 =
1'
#6260000
0'
#6270000
b1010001 =
b10111011 2
1'
#6280000
0'
#6290000
b10111100 2
b1010010 =
1'
#6300000
0'
#6310000
b1010011 =
b10111101 2
1'
#6320000
0'
#6330000
b10111110 2
b1010100 =
1'
#6340000
0'
#6350000
b1010101 =
b10111111 2
1'
#6360000
0'
#6370000
b11000000 2
b1010110 =
1'
#6380000
0'
#6390000
b1010111 =
b11000001 2
1'
#6400000
0'
#6410000
b11000010 2
b1011000 =
1'
#6420000
0'
#6430000
b1011001 =
b11000011 2
1'
#6440000
0'
#6450000
b11000100 2
b1011010 =
1'
#6460000
0'
#6470000
b1011011 =
b11000101 2
1'
#6480000
0'
#6490000
b11000110 2
b1011100 =
1'
#6500000
0'
#6510000
b1011101 =
b11000111 2
1'
#6520000
0'
#6530000
b11001000 2
b1011110 =
1'
#6540000
0'
#6550000
b1011111 =
b11001001 2
1'
#6560000
0'
#6570000
b11001010 2
b1100000 =
1'
#6580000
0'
#6590000
b1100001 =
b11001011 2
1'
#6600000
0'
#6610000
b11001100 2
b1100010 =
1'
#6620000
0'
#6630000
b1100011 =
b11001101 2
1'
#6640000
0'
#6650000
b11001110 2
b1100100 =
1'
#6660000
0'
#6670000
b1100101 =
b11001111 2
1'
#6680000
0'
#6690000
b11010000 2
b1100110 =
1'
#6700000
0'
#6710000
b1100111 =
b11010001 2
1'
#6720000
0'
#6730000
b11010010 2
b1101000 =
1'
#6740000
0'
#6750000
b1101001 =
b11010011 2
1'
#6760000
0'
#6770000
b11010100 2
b1101010 =
1'
#6780000
0'
#6790000
b1101011 =
b11010101 2
1'
#6800000
0'
#6810000
b11010110 2
b1101100 =
1'
#6820000
0'
#6830000
b1101101 =
b11010111 2
1'
#6840000
0'
#6850000
b11011000 2
b1101110 =
1'
#6860000
0'
#6870000
b1101111 =
b1 1
bx1 %
bx1 3
b0 2
1'
#6880000
0'
#6890000
b1 2
b1110000 =
1'
#6900000
0'
#6910000
b1110001 =
b10 2
1'
#6920000
0'
#6930000
b11 2
b1110010 =
1'
#6940000
0'
#6950000
b1110011 =
b100 2
1'
#6960000
0'
#6970000
b101 2
b1110100 =
1'
#6980000
0'
#6990000
b1110101 =
b110 2
1'
#7000000
0'
#7010000
b111 2
b1110110 =
1'
#7020000
0'
#7030000
b1110111 =
b1000 2
1'
#7040000
0'
#7050000
b1001 2
b1111000 =
1'
#7060000
0'
#7070000
b1111001 =
b1010 2
1'
#7080000
0'
#7090000
b1011 2
b1111010 =
1'
#7100000
0'
#7110000
b1111011 =
b1100 2
1'
#7120000
0'
#7130000
b1101 2
b1111100 =
1'
#7140000
0'
#7150000
b1111101 =
b1110 2
1'
#7160000
0'
#7170000
b1111 2
b1111110 =
1'
#7180000
0'
#7190000
b1111111 =
b10000 2
1'
#7200000
0'
#7210000
b10001 2
b10000000 =
1'
#7220000
0'
#7230000
b10000001 =
b10010 2
1'
#7240000
0'
#7250000
b10011 2
b10000010 =
1'
#7260000
0'
#7270000
b10000011 =
b10100 2
1'
#7280000
0'
#7290000
b10101 2
b10000100 =
1'
#7300000
0'
#7310000
b10000101 =
b10110 2
1'
#7320000
0'
#7330000
b10111 2
b10000110 =
1'
#7340000
0'
#7350000
b10000111 =
b11000 2
1'
#7360000
0'
#7370000
b11001 2
b10001000 =
1'
#7380000
0'
#7390000
b10001001 =
b11010 2
1'
#7400000
0'
#7410000
b11011 2
b10001010 =
1'
#7420000
0'
#7430000
b10001011 =
b11100 2
1'
#7440000
0'
#7450000
b11101 2
b10001100 =
1'
#7460000
0'
#7470000
b10001101 =
b11110 2
1'
#7480000
0'
#7490000
b11111 2
b10001110 =
1'
#7500000
0'
